fib.py
setup.py
uu_fibonacci.egg-info/PKG-INFO
uu_fibonacci.egg-info/SOURCES.txt
uu_fibonacci.egg-info/dependency_links.txt
uu_fibonacci.egg-info/top_level.txt