Metadata-Version: 1.0
Name: uu-fibonacci
Version: 1.0
Summary: Example package that calculates fibonacci numbers
Home-page: https://github.com/uu-python/travis-fib
Author: Filipe Maia
Author-email: filipe.c.maia@gmail.com
License: BSD
Platform: UNKNOWN
